ilearnplus/__init__.py
ilearnplus/iLearnPlus.py
ilearnplus/iLearnPlusAutoML.py
ilearnplus/iLearnPlusBasic.py
ilearnplus/iLearnPlusEstimator.py
ilearnplus/iLearnPlusLoadModel.py
ilearnplus/data/ANF.csv
ilearnplus/data/DNA_sequences.txt
ilearnplus/data/Data_for_boxplot.tsv
ilearnplus/data/Data_for_heatmap.tsv
ilearnplus/data/Kmer.csv
ilearnplus/data/Lysine_crotonylation.txt
ilearnplus/data/Malonylation.txt
ilearnplus/data/Merged_ANF_and_Kmer.csv
ilearnplus/data/RNA_sequences.txt
ilearnplus/data/binary.csv
ilearnplus/data/binary_ind.csv
ilearnplus/data/data.csv
ilearnplus/data/data_for_hist.tsv
ilearnplus/data/data_for_roc1.tsv
ilearnplus/data/data_for_roc_curve.tsv
ilearnplus/data/data_for_scatter_plot.tsv
ilearnplus/data/lncRNA_sequences.txt
ilearnplus/data/m1A_DNA_sequences.txt
ilearnplus/data/mutitask.tsv
ilearnplus/data/peptide_sequences.txt
ilearnplus/docs/iLearnPlus_manual.pdf
ilearnplus/images/Architecture.png
ilearnplus/images/AutoML.png
ilearnplus/images/Basic.png
ilearnplus/images/Case_1.png
ilearnplus/images/Case_2.png
ilearnplus/images/DataVisualization.png
ilearnplus/images/Estimator.png
ilearnplus/images/LoadModel.png
ilearnplus/images/iLearnPlus.png
ilearnplus/images/logo.ico
ilearnplus/images/logo.png
ilearnplus/images/progress_bar.gif
ilearnplus/models/SVM_model_1.pkl
ilearnplus/models/SVM_model_2.pkl
ilearnplus/models/SVM_model_3.pkl
ilearnplus/models/SVM_model_4.pkl
ilearnplus/models/SVM_model_5.pkl
ilearnplus/util/CheckAccPseParameter.py
ilearnplus/util/DataAnalysis.py
ilearnplus/util/EvaluationMetrics.py
ilearnplus/util/FileProcessing.py
ilearnplus/util/InputDialog.py
ilearnplus/util/MCL.py
ilearnplus/util/MachineLearning.py
ilearnplus/util/ModelMetrics.py
ilearnplus/util/Modules.py
ilearnplus/util/Nets.py
ilearnplus/util/PlotWidgets.py
ilearnplus/util/TableWidget.py
ilearnplus/util/__init__.py
ilearnplus/util/data/AAidx.txt
ilearnplus/util/data/AAindex.data
ilearnplus/util/data/AAindex.txt
ilearnplus/util/data/CTD.txt
ilearnplus-1.5.dist-info/METADATA
ilearnplus-1.5.dist-info/WHEEL
ilearnplus-1.5.dist-info/top_level.txt
ilearnplus-1.5.dist-info/RECORD
