Metadata-Version: 2.1
Name: ilearnplus
Version: 1.5
Summary: A comprehensive and automated machine-learning platform for nucleic acid and protein sequence analysis, prediction and visualization
Home-page: https://github.com/Superzchen/iLearnPlus
Author: SuperZhen
Author-email: chenzhen-win2009@163.com
License: MIT License
Keywords: ilearnplus
Platform: any
Requires-Dist: qdarkstyle
Requires-Dist: numpy >=1.18.5
Requires-Dist: pandas >=1.0.5
Requires-Dist: sip
Requires-Dist: datetime
Requires-Dist: scikit-learn >=0.23.1
Requires-Dist: scipy >=1.5.0
Requires-Dist: lightgbm
Requires-Dist: xgboost
Requires-Dist: matplotlib >=3.1.1
Requires-Dist: seaborn
Requires-Dist: joblib
